quillow/__init__.py
quillow/api/__init__.py
quillow/api/cli.py
quillow/backends/__init__.py
quillow/backends/abstract_backend.py
quillow/backends/bioql_backend.py
quillow/backends/stim_backend.py
quillow/core/__init__.py
quillow/core/color_code.py
quillow/core/noise_models.py
quillow/core/pauli_frame.py
quillow/core/surface_code.py
quillow/core/syndrome.py
quillow/decoders/__init__.py
quillow/decoders/abstract_decoder.py
quillow/decoders/gpu_decoder_modal.py
quillow/decoders/mwpm.py
quillow/decoders/union_find.py
quillow-2.0.1.dist-info/licenses/LICENSE
quillow-2.0.1.dist-info/METADATA
quillow-2.0.1.dist-info/WHEEL
quillow-2.0.1.dist-info/entry_points.txt
quillow-2.0.1.dist-info/top_level.txt
quillow-2.0.1.dist-info/RECORD
