Metadata-Version: 2.4
Name: quillow
Version: 2.0.1
Summary: Willow-style quantum error correction framework with surface codes, MWPM decoding, and real quantum hardware integration
Home-page: https://bioql.bio/quillow
Author: SpectrixRD
Author-email: SpectrixRD <contact@spectrixrd.com>
Maintainer-email: SpectrixRD <contact@spectrixrd.com>
License: MIT
Project-URL: Homepage, https://github.com/spectrixrd/quillow
Project-URL: Documentation, https://quillow.readthedocs.io
Project-URL: Repository, https://github.com/spectrixrd/quillow
Project-URL: Bug Tracker, https://github.com/spectrixrd/quillow/issues
Project-URL: BioQL Platform, https://bioql.bio
Keywords: quantum computing,quantum error correction,surface codes,fault-tolerant,MWPM,syndrome decoding,Willow,BioQL,quantum chemistry
Platform: any
Classifier: Development Status :: 4 - Beta
Classifier: Intended Audience :: Science/Research
Classifier: Intended Audience :: Developers
Classifier: License :: OSI Approved :: MIT License
Classifier: Operating System :: OS Independent
Classifier: Programming Language :: Python :: 3
Classifier: Programming Language :: Python :: 3.9
Classifier: Programming Language :: Python :: 3.10
Classifier: Programming Language :: Python :: 3.11
Classifier: Programming Language :: Python :: 3.12
Classifier: Topic :: Scientific/Engineering :: Physics
Classifier: Topic :: Scientific/Engineering :: Chemistry
Classifier: Topic :: Scientific/Engineering :: Information Analysis
Classifier: Framework :: AsyncIO
Requires-Python: >=3.9
License-File: LICENSE
Requires-Dist: stim>=1.12.0
Requires-Dist: pymatching>=2.0.0
Requires-Dist: numpy>=1.21.0
Requires-Dist: scipy>=1.7.0
Requires-Dist: numba>=0.56.0
Requires-Dist: matplotlib>=3.5.0
Requires-Dist: networkx>=2.8.0
Requires-Dist: tqdm>=4.64.0
Requires-Dist: click>=8.0.0
Requires-Dist: pyyaml>=6.0
Requires-Dist: loguru>=0.6.0
Requires-Dist: pydantic>=2.0.0
Requires-Dist: requests>=2.28.0
Provides-Extra: gpu
Requires-Dist: torch>=2.0.0; extra == "gpu"
Requires-Dist: cupy>=12.0.0; extra == "gpu"
Provides-Extra: cloud
Requires-Dist: modal>=0.55.0; extra == "cloud"
Provides-Extra: dev
Requires-Dist: pytest>=7.0.0; extra == "dev"
Requires-Dist: pytest-cov>=4.0.0; extra == "dev"
Requires-Dist: pytest-asyncio>=0.21.0; extra == "dev"
Requires-Dist: black>=22.0.0; extra == "dev"
Requires-Dist: flake8>=5.0.0; extra == "dev"
Requires-Dist: mypy>=0.991; extra == "dev"
Requires-Dist: build>=0.10.0; extra == "dev"
Requires-Dist: twine>=4.0.0; extra == "dev"
Provides-Extra: api
Requires-Dist: fastapi>=0.100.0; extra == "api"
Requires-Dist: uvicorn>=0.23.0; extra == "api"
Provides-Extra: all
Requires-Dist: torch>=2.0.0; extra == "all"
Requires-Dist: cupy>=12.0.0; extra == "all"
Requires-Dist: modal>=0.55.0; extra == "all"
Requires-Dist: fastapi>=0.100.0; extra == "all"
Requires-Dist: uvicorn>=0.23.0; extra == "all"
Dynamic: author
Dynamic: home-page
Dynamic: license-file
Dynamic: platform
Dynamic: requires-python
